MANIFEST.in
setup.py
cxx/PyArray.hxx
cxx/PyBytesSink.hxx
cxx/PythonSeekableFile.hxx
cxx/Swizzle.cxx
cxx/Swizzle.hxx
cxx/base64.cxx
cxx/base64.h
cxx/block_file.hxx
cxx/clz.h
cxx/config.h
cxx/endian_swap.h
cxx/heartbeat.hxx
cxx/integer_block_file_interface.hxx
cxx/pointer.hxx
cxx/prf.hxx
cxx/prf_test.cxx
cxx/seekable_file.hxx
cxx/serializable.hxx
cxx/shacham_waters_private.cxx
cxx/shacham_waters_private.hxx
cxx/simple_file.hxx
cxx/stream_block_file.hxx
cxx/stream_file.hxx
cxx/test.cxx
cxx/pycxx/Src/IndirectPythonInterface.cxx
cxx/pycxx/Src/cxx_extensions.cxx
cxx/pycxx/Src/cxxextensions.c
cxx/pycxx/Src/cxxsupport.cxx
cxx/pycxx/CXX/Config.hxx
cxx/pycxx/CXX/Exception.hxx
cxx/pycxx/CXX/Extensions.hxx
cxx/pycxx/CXX/IndirectPythonInterface.hxx
cxx/pycxx/CXX/Objects.hxx
cxx/pycxx/CXX/Version.hxx
cxx/pycxx/CXX/WrapPython.h
cxx/pycxx/CXX/Python2/Config.hxx
cxx/pycxx/CXX/Python2/CxxDebug.hxx
cxx/pycxx/CXX/Python2/Exception.hxx
cxx/pycxx/CXX/Python2/ExtensionModule.hxx
cxx/pycxx/CXX/Python2/ExtensionOldType.hxx
cxx/pycxx/CXX/Python2/ExtensionType.hxx
cxx/pycxx/CXX/Python2/ExtensionTypeBase.hxx
cxx/pycxx/CXX/Python2/Extensions.hxx
cxx/pycxx/CXX/Python2/IndirectPythonInterface.hxx
cxx/pycxx/CXX/Python2/Objects.hxx
cxx/pycxx/CXX/Python2/PythonType.hxx
cxx/pycxx/CXX/Python3/Config.hxx
cxx/pycxx/CXX/Python3/CxxDebug.hxx
cxx/pycxx/CXX/Python3/Exception.hxx
cxx/pycxx/CXX/Python3/ExtensionModule.hxx
cxx/pycxx/CXX/Python3/ExtensionOldType.hxx
cxx/pycxx/CXX/Python3/ExtensionType.hxx
cxx/pycxx/CXX/Python3/ExtensionTypeBase.hxx
cxx/pycxx/CXX/Python3/Extensions.hxx
cxx/pycxx/CXX/Python3/IndirectPythonInterface.hxx
cxx/pycxx/CXX/Python3/Objects.hxx
cxx/pycxx/CXX/Python3/PythonType.hxx
cxx/pycxx/Src/IndirectPythonInterface.cxx
cxx/pycxx/Src/cxx_extensions.cxx
cxx/pycxx/Src/cxxextensions.c
cxx/pycxx/Src/cxxsupport.cxx
cxx/pycxx/Src/Python2/cxx_extensions.cxx
cxx/pycxx/Src/Python2/cxxextensions.c
cxx/pycxx/Src/Python2/cxxsupport.cxx
cxx/pycxx/Src/Python3/cxx_extensions.cxx
storj_heartbeat.egg-info/PKG-INFO
storj_heartbeat.egg-info/SOURCES.txt
storj_heartbeat.egg-info/dependency_links.txt
storj_heartbeat.egg-info/requires.txt
storj_heartbeat.egg-info/top_level.txt