Metadata-Version: 1.0
Name: storj-heartbeat
Version: 0.1.10
Summary: Python library for verifying existence of a file
Home-page: https://github.com/Storj/heartbeat
Author: Storj Labs
Author-email: info@storj.io
License: The MIT License
Platform: UNKNOWN
